asknews_sdk/__init__.py
asknews_sdk/api/__init__.py
asknews_sdk/api/base.py
asknews_sdk/api/chat.py
asknews_sdk/api/news.py
asknews_sdk/api/sentiment.py
asknews_sdk/api/stories.py
asknews_sdk/client.py
asknews_sdk/dto/__init__.py
asknews_sdk/dto/base.py
asknews_sdk/dto/chat.py
asknews_sdk/dto/error.py
asknews_sdk/dto/news.py
asknews_sdk/dto/sentiment.py
asknews_sdk/dto/stories.py
asknews_sdk/errors.py
asknews_sdk/sdk.py
asknews_sdk/security.py
asknews_sdk/utils.py
asknews_sdk/version.py
asknews_sdk-0.3.3.dist-info/LICENSE
asknews_sdk-0.3.3.dist-info/METADATA
asknews_sdk-0.3.3.dist-info/WHEEL
asknews_sdk-0.3.3.dist-info/RECORD
