Metadata-Version: 2.1
Name: asknews_sdk
Version: 0.3.3
Summary: Python SDK for AskNews
Home-page: https://gitlab.com/asknews/python-sdk
License: MIT
Author: Emergent Methods
Author-email: contact@emergentmethods.ai
Requires-Python: >=3.10,<4.0
Classifier: License :: OSI Approved :: MIT License
Classifier: Programming Language :: Python :: 3
Classifier: Programming Language :: Python :: 3.10
Classifier: Programming Language :: Python :: 3.11
Classifier: Programming Language :: Python :: 3.12
Requires-Dist: authlib (>=1.3.0,<2.0.0)
Requires-Dist: httpx (>=0.25.2,<0.26.0)
Requires-Dist: orjson (>=3.9.10,<4.0.0)
Requires-Dist: pydantic (>=2.5.3,<3.0.0)
Project-URL: Repository, https://gitlab.com/asknews/python-sdk
